<?xml version="1.0" encoding="UTF-8" standalone="no"?>
<ResultsSession>
   <SessionData configName="700120 rule set 2024" configPseudoUrl="c++test.user://700120 rule set 2024" enabledAnalysis="Static" enabledHandlers="com.parasoft.xtest.checkers.api.scope.factory;com.parasoft.xtest.checkers.api.standards.factory" hasViols="true" header="??:TheOrb:??true??false??" runId="" startTime="1766505027998" tool="c++test">
      <TestParameters cmdLn="C++test: -config c++test.user://700120 rule set 2024 "/>
      <Authors>
         <Author id="dev1" name="a"/>
      </Authors>
      <Selection>
         <Res id="TheOrb/TheOrb/Source Files/src/geometry/OBJLoader.cpp"/>
         <Res id="TheOrb/TheOrb/Source Files/src/vulkan/VulkanContext.h"/>
         <Res id="TheOrb/TheOrb/Source Files/src/rendering/Cubemap.h"/>
         <Res id="TheOrb/TheOrb/Source Files/src/rendering/Scene.cpp"/>
         <Res id="TheOrb/TheOrb/Source Files/src/vulkan/VulkanRenderPass.h"/>
         <Res id="TheOrb/TheOrb/Source Files/src/main.cpp"/>
         <Res id="TheOrb/TheOrb/Source Files/src/vulkan"/>
         <Res id="TheOrb/TheOrb/Source Files/src/rendering/SkyboxPass.cpp"/>
         <Res id="TheOrb/TheOrb/Source Files/src/vulkan/VulkanDevice.cpp"/>
         <Res id="TheOrb/TheOrb/Source Files/src/rendering"/>
         <Res id="TheOrb/TheOrb/Source Files/src/rendering/Renderer.cpp"/>
         <Res id="TheOrb/TheOrb/Source Files/src/rendering/ShadowPass.h"/>
         <Res id="TheOrb/TheOrb/Source Files/src/geometry"/>
         <Res id="TheOrb/TheOrb/Source Files/src/rendering/GraphicsPipeline.h"/>
         <Res id="TheOrb/TheOrb/Source Files/src/rendering/SkyboxPass.h"/>
         <Res id="TheOrb/TheOrb/Source Files/src/rendering/Cubemap.cpp"/>
         <Res id="TheOrb/TheOrb/Source Files/src/vulkan/PushConstantObject.h"/>
         <Res id="TheOrb/TheOrb/Source Files/src/rendering/Texture.cpp"/>
         <Res id="TheOrb/TheOrb/Source Files/src/rendering/ParticleSystem.h"/>
         <Res id="TheOrb/TheOrb/Source Files/src/geometry/OBJLoader.h"/>
         <Res id="TheOrb/TheOrb/Source Files/src/vulkan/VulkanShader.h"/>
         <Res id="TheOrb/TheOrb/Source Files/src/core/Window.h"/>
         <Res id="TheOrb/TheOrb/Source Files/src/rendering/ParticleLibrary.h"/>
         <Res id="TheOrb/TheOrb/Source Files/src/core/Window.cpp"/>
         <Res id="TheOrb/TheOrb/Source Files/src/rendering/ShadowPass.cpp"/>
         <Res id="TheOrb/TheOrb/Source Files/src/shader/particle.frag"/>
         <Res id="TheOrb/TheOrb/Source Files/src/vulkan/Vertex.h"/>
         <Res id="TheOrb/TheOrb/Source Files/src/shader/particle.vert"/>
         <Res id="TheOrb/TheOrb/Source Files/src/rendering/Texture.h"/>
         <Res id="TheOrb/TheOrb/Source Files/src/vulkan/VulkanBuffer.h"/>
         <Res id="TheOrb/TheOrb/Source Files/src/vulkan/VulkanUtils.h"/>
         <Res id="TheOrb/TheOrb/Source Files/src/geometry/Geometry.cpp"/>
         <Res id="TheOrb/TheOrb/Source Files/src/geometry/GeometryGenerator.cpp"/>
         <Res id="TheOrb/TheOrb/Source Files/src/vulkan/VulkanRenderPass.cpp"/>
         <Res id="TheOrb/TheOrb/Source Files/src/rendering/GraphicsPipeline.cpp"/>
         <Res id="TheOrb/TheOrb/Source Files/src/vulkan/VulkanContext.cpp"/>
         <Res id="TheOrb/TheOrb/Source Files/src/vulkan/VulkanUtils.cpp"/>
         <Res id="TheOrb/TheOrb/Source Files/src/rendering/CameraController.cpp"/>
         <Res id="TheOrb/TheOrb/Source Files/src/shader/shader.vert"/>
         <Res id="TheOrb/TheOrb/Source Files/src/rendering/Camera.cpp"/>
         <Res id="TheOrb/TheOrb/Source Files/src/shader/skybox.frag"/>
         <Res id="TheOrb/TheOrb/Source Files/src/rendering/Camera.h"/>
         <Res id="TheOrb/TheOrb/Source Files/src/vulkan/VulkanDescriptorSet.h"/>
         <Res id="TheOrb/TheOrb/Source Files/src/rendering/CameraController.h"/>
         <Res id="TheOrb/TheOrb/Source Files/src/vulkan/VulkanBuffer.cpp"/>
         <Res id="TheOrb/TheOrb/Source Files/src/core/Application.h"/>
         <Res id="TheOrb/TheOrb/Source Files/src/vulkan/VulkanSwapChain.cpp"/>
         <Res id="TheOrb/TheOrb/Source Files/src/vulkan/VulkanSyncObjects.h"/>
         <Res id="TheOrb/TheOrb/Source Files/src/vulkan/VulkanCommandBuffer.h"/>
         <Res id="TheOrb/TheOrb/Source Files/src/rendering/Renderer.h"/>
         <Res id="TheOrb/TheOrb/Source Files/src/vulkan/VulkanCommandBuffer.cpp"/>
         <Res id="TheOrb/TheOrb/Source Files/src/rendering/ParticleLibrary.cpp"/>
         <Res id="TheOrb/TheOrb/Source Files/src/shader/skybox.vert"/>
         <Res id="TheOrb/TheOrb/Source Files/src/vulkan/VulkanShader.cpp"/>
         <Res id="TheOrb/TheOrb/Source Files/src/rendering/ParticleSystem.cpp"/>
         <Res id="TheOrb/TheOrb/Source Files/src/vulkan/UniformBufferObject.h"/>
         <Res id="TheOrb/TheOrb/Source Files/src/shader"/>
         <Res id="TheOrb/TheOrb/Source Files/src/shader/shadow.vert"/>
         <Res id="TheOrb/TheOrb/Source Files/src/shader/shadow.frag"/>
         <Res id="TheOrb/TheOrb/Source Files/src/vulkan/VulkanDevice.h"/>
         <Res id="TheOrb/TheOrb/Source Files/src/vulkan/VulkanSyncObjects.cpp"/>
         <Res id="TheOrb/TheOrb/Source Files/src/shader/shader.frag"/>
         <Res id="TheOrb/TheOrb/Source Files/src/vulkan/VulkanDescriptorSet.cpp"/>
         <Res id="TheOrb/TheOrb/Source Files/src/rendering/Scene.h"/>
         <Res id="TheOrb/TheOrb/Source Files/src/vulkan/VulkanSwapChain.h"/>
         <Res id="TheOrb/TheOrb/Source Files/src/geometry/GeometryGenerator.h"/>
         <Res id="TheOrb/TheOrb/Source Files/src/core/Application.cpp"/>
         <Res id="TheOrb/TheOrb/Source Files/src/geometry/Geometry.h"/>
      </Selection>
      <XmlDataFiles file0="C:\Users\a\Desktop\TheOrb\.parasoft.dat\.solutions\TheOrb\session_results_report_xml\cs_violations.xml"/>
   </SessionData>
   <Locations>
      <Loc fsPath="C:\Users\a\Desktop\TheOrb\src\geometry\GeometryGenerator.cpp" loc="TheOrb/TheOrb/Source Files/src/geometry/GeometryGenerator.cpp" projPath="TheOrb/TheOrb" project="TheOrb"/>
      <Loc fsPath="C:\Users\a\Desktop\TheOrb\src\geometry\OBJLoader.cpp" loc="TheOrb/TheOrb/Source Files/src/geometry/OBJLoader.cpp" projPath="TheOrb/TheOrb" project="TheOrb"/>
      <Loc fsPath="C:\Users\a\Desktop\TheOrb\src\vulkan\VulkanContext.h" loc="TheOrb/TheOrb/Source Files/src/vulkan/VulkanContext.h" projPath="TheOrb/TheOrb" project="TheOrb"/>
      <Loc fsPath="C:\Users\a\Desktop\TheOrb\src\vulkan\VulkanContext.cpp" loc="TheOrb/TheOrb/Source Files/src/vulkan/VulkanContext.cpp" projPath="TheOrb/TheOrb" project="TheOrb"/>
      <Loc fsPath="C:\Users\a\Desktop\TheOrb\src\vulkan\VulkanUtils.cpp" loc="TheOrb/TheOrb/Source Files/src/vulkan/VulkanUtils.cpp" projPath="TheOrb/TheOrb" project="TheOrb"/>
      <Loc fsPath="C:\Users\a\Desktop\TheOrb\src\rendering\Scene.cpp" loc="TheOrb/TheOrb/Source Files/src/rendering/Scene.cpp" projPath="TheOrb/TheOrb" project="TheOrb"/>
      <Loc fsPath="C:\Users\a\Desktop\TheOrb\src\vulkan\VulkanRenderPass.h" loc="TheOrb/TheOrb/Source Files/src/vulkan/VulkanRenderPass.h" projPath="TheOrb/TheOrb" project="TheOrb"/>
      <Loc fsPath="C:\Users\a\Desktop\TheOrb\src\rendering\Camera.h" loc="TheOrb/TheOrb/Source Files/src/rendering/Camera.h" projPath="TheOrb/TheOrb" project="TheOrb"/>
      <Loc fsPath="C:\Users\a\Desktop\TheOrb\src\vulkan\VulkanDescriptorSet.h" loc="TheOrb/TheOrb/Source Files/src/vulkan/VulkanDescriptorSet.h" projPath="TheOrb/TheOrb" project="TheOrb"/>
      <Loc fsPath="C:\Users\a\Desktop\TheOrb\src\rendering\SkyboxPass.cpp" loc="TheOrb/TheOrb/Source Files/src/rendering/SkyboxPass.cpp" projPath="TheOrb/TheOrb" project="TheOrb"/>
      <Loc fsPath="C:\Users\a\Desktop\TheOrb\src\vulkan\VulkanDevice.cpp" loc="TheOrb/TheOrb/Source Files/src/vulkan/VulkanDevice.cpp" projPath="TheOrb/TheOrb" project="TheOrb"/>
      <Loc fsPath="C:\Users\a\Desktop\TheOrb\src\vulkan\VulkanSwapChain.cpp" loc="TheOrb/TheOrb/Source Files/src/vulkan/VulkanSwapChain.cpp" projPath="TheOrb/TheOrb" project="TheOrb"/>
      <Loc fsPath="C:\Users\a\Desktop\TheOrb\src\rendering\Renderer.cpp" loc="TheOrb/TheOrb/Source Files/src/rendering/Renderer.cpp" projPath="TheOrb/TheOrb" project="TheOrb"/>
      <Loc fsPath="C:\Users\a\Desktop\TheOrb\src\vulkan\VulkanSyncObjects.h" loc="TheOrb/TheOrb/Source Files/src/vulkan/VulkanSyncObjects.h" projPath="TheOrb/TheOrb" project="TheOrb"/>
      <Loc fsPath="C:\Users\a\Desktop\TheOrb\src\vulkan\VulkanCommandBuffer.h" loc="TheOrb/TheOrb/Source Files/src/vulkan/VulkanCommandBuffer.h" projPath="TheOrb/TheOrb" project="TheOrb"/>
      <Loc fsPath="C:\Users\a\Desktop\TheOrb\src\rendering\Renderer.h" loc="TheOrb/TheOrb/Source Files/src/rendering/Renderer.h" projPath="TheOrb/TheOrb" project="TheOrb"/>
      <Loc fsPath="C:\Users\a\Desktop\TheOrb\src\vulkan\VulkanCommandBuffer.cpp" loc="TheOrb/TheOrb/Source Files/src/vulkan/VulkanCommandBuffer.cpp" projPath="TheOrb/TheOrb" project="TheOrb"/>
      <Loc fsPath="C:\Users\a\Desktop\TheOrb\src\rendering\ParticleLibrary.cpp" loc="TheOrb/TheOrb/Source Files/src/rendering/ParticleLibrary.cpp" projPath="TheOrb/TheOrb" project="TheOrb"/>
      <Loc fsPath="C:\Users\a\Desktop\TheOrb\src\rendering\ShadowPass.h" loc="TheOrb/TheOrb/Source Files/src/rendering/ShadowPass.h" projPath="TheOrb/TheOrb" project="TheOrb"/>
      <Loc fsPath="C:\Users\a\Desktop\TheOrb\src\rendering\SkyboxPass.h" loc="TheOrb/TheOrb/Source Files/src/rendering/SkyboxPass.h" projPath="TheOrb/TheOrb" project="TheOrb"/>
      <Loc fsPath="C:\Users\a\Desktop\TheOrb\src\rendering\GraphicsPipeline.h" loc="TheOrb/TheOrb/Source Files/src/rendering/GraphicsPipeline.h" projPath="TheOrb/TheOrb" project="TheOrb"/>
      <Loc fsPath="C:\Users\a\Desktop\TheOrb\src\rendering\ParticleSystem.cpp" loc="TheOrb/TheOrb/Source Files/src/rendering/ParticleSystem.cpp" projPath="TheOrb/TheOrb" project="TheOrb"/>
      <Loc fsPath="C:\Users\a\Desktop\TheOrb\src\vulkan\UniformBufferObject.h" loc="TheOrb/TheOrb/Source Files/src/vulkan/UniformBufferObject.h" projPath="TheOrb/TheOrb" project="TheOrb"/>
      <Loc fsPath="C:\Users\a\Desktop\TheOrb\src\rendering\Texture.cpp" loc="TheOrb/TheOrb/Source Files/src/rendering/Texture.cpp" projPath="TheOrb/TheOrb" project="TheOrb"/>
      <Loc fsPath="C:\Users\a\Desktop\TheOrb\src\rendering\ParticleSystem.h" loc="TheOrb/TheOrb/Source Files/src/rendering/ParticleSystem.h" projPath="TheOrb/TheOrb" project="TheOrb"/>
      <Loc fsPath="C:\Users\a\Desktop\TheOrb\src\core\Window.h" loc="TheOrb/TheOrb/Source Files/src/core/Window.h" projPath="TheOrb/TheOrb" project="TheOrb"/>
      <Loc fsPath="C:\Users\a\Desktop\TheOrb\src\geometry\OBJLoader.h" loc="TheOrb/TheOrb/Source Files/src/geometry/OBJLoader.h" projPath="TheOrb/TheOrb" project="TheOrb"/>
      <Loc fsPath="C:\Users\a\Desktop\TheOrb\src\vulkan\VulkanDevice.h" loc="TheOrb/TheOrb/Source Files/src/vulkan/VulkanDevice.h" projPath="TheOrb/TheOrb" project="TheOrb"/>
      <Loc fsPath="C:\Users\a\Desktop\TheOrb\src\core\Window.cpp" loc="TheOrb/TheOrb/Source Files/src/core/Window.cpp" projPath="TheOrb/TheOrb" project="TheOrb"/>
      <Loc fsPath="C:\Users\a\Desktop\TheOrb\src\rendering\Scene.h" loc="TheOrb/TheOrb/Source Files/src/rendering/Scene.h" projPath="TheOrb/TheOrb" project="TheOrb"/>
      <Loc fsPath="C:\Users\a\Desktop\TheOrb\src\vulkan\VulkanSwapChain.h" loc="TheOrb/TheOrb/Source Files/src/vulkan/VulkanSwapChain.h" projPath="TheOrb/TheOrb" project="TheOrb"/>
      <Loc fsPath="C:\Users\a\Desktop\TheOrb\src\geometry\GeometryGenerator.h" loc="TheOrb/TheOrb/Source Files/src/geometry/GeometryGenerator.h" projPath="TheOrb/TheOrb" project="TheOrb"/>
      <Loc fsPath="C:\Users\a\Desktop\TheOrb\src\geometry\Geometry.h" loc="TheOrb/TheOrb/Source Files/src/geometry/Geometry.h" projPath="TheOrb/TheOrb" project="TheOrb"/>
   </Locations>
   <CodingStandards>
      <TestedFilesDetails>
         <Total name="Suppressed / Total" supp="0" total="95">
            <Project name="TheOrb" supp="0" total="95">
               <Res name="Source Files/src/geometry" supp="0" total="18">
                  <Res loc="TheOrb/TheOrb/Source Files/src/geometry/OBJLoader.cpp" locType="sr" name="OBJLoader.cpp" supp="0" total="1"/>
                  <Res loc="TheOrb/TheOrb/Source Files/src/geometry/OBJLoader.h" locType="sr" name="OBJLoader.h" supp="0" total="1"/>
                  <Res name="Geometry.cpp" supp="0" total="0"/>
                  <Res loc="TheOrb/TheOrb/Source Files/src/geometry/GeometryGenerator.cpp" locType="sr" name="GeometryGenerator.cpp" supp="0" total="6"/>
                  <Res loc="TheOrb/TheOrb/Source Files/src/geometry/GeometryGenerator.h" locType="sr" name="GeometryGenerator.h" supp="0" total="6"/>
                  <Res loc="TheOrb/TheOrb/Source Files/src/geometry/Geometry.h" locType="sr" name="Geometry.h" supp="0" total="4"/>
               </Res>
               <Res name="Source Files/src/vulkan" supp="0" total="45">
                  <Res loc="TheOrb/TheOrb/Source Files/src/vulkan/VulkanContext.h" locType="sr" name="VulkanContext.h" supp="0" total="3"/>
                  <Res loc="TheOrb/TheOrb/Source Files/src/vulkan/VulkanRenderPass.h" locType="sr" name="VulkanRenderPass.h" supp="0" total="5"/>
                  <Res loc="TheOrb/TheOrb/Source Files/src/vulkan/VulkanDevice.cpp" locType="sr" name="VulkanDevice.cpp" supp="0" total="1"/>
                  <Res name="PushConstantObject.h" supp="0" total="0"/>
                  <Res name="VulkanShader.h" supp="0" total="0"/>
                  <Res name="Vertex.h" supp="0" total="0"/>
                  <Res name="VulkanBuffer.h" supp="0" total="0"/>
                  <Res name="VulkanUtils.h" supp="0" total="0"/>
                  <Res name="VulkanRenderPass.cpp" supp="0" total="0"/>
                  <Res loc="TheOrb/TheOrb/Source Files/src/vulkan/VulkanContext.cpp" locType="sr" name="VulkanContext.cpp" supp="0" total="3"/>
                  <Res loc="TheOrb/TheOrb/Source Files/src/vulkan/VulkanUtils.cpp" locType="sr" name="VulkanUtils.cpp" supp="0" total="3"/>
                  <Res loc="TheOrb/TheOrb/Source Files/src/vulkan/VulkanDescriptorSet.h" locType="sr" name="VulkanDescriptorSet.h" supp="0" total="2"/>
                  <Res name="VulkanBuffer.cpp" supp="0" total="0"/>
                  <Res loc="TheOrb/TheOrb/Source Files/src/vulkan/VulkanSwapChain.cpp" locType="sr" name="VulkanSwapChain.cpp" supp="0" total="4"/>
                  <Res loc="TheOrb/TheOrb/Source Files/src/vulkan/VulkanSyncObjects.h" locType="sr" name="VulkanSyncObjects.h" supp="0" total="4"/>
                  <Res loc="TheOrb/TheOrb/Source Files/src/vulkan/VulkanCommandBuffer.h" locType="sr" name="VulkanCommandBuffer.h" supp="0" total="2"/>
                  <Res loc="TheOrb/TheOrb/Source Files/src/vulkan/VulkanCommandBuffer.cpp" locType="sr" name="VulkanCommandBuffer.cpp" supp="0" total="2"/>
                  <Res loc="TheOrb/TheOrb/Source Files/src/vulkan/UniformBufferObject.h" locType="sr" name="UniformBufferObject.h" supp="0" total="2"/>
                  <Res name="VulkanShader.cpp" supp="0" total="0"/>
                  <Res loc="TheOrb/TheOrb/Source Files/src/vulkan/VulkanDevice.h" locType="sr" name="VulkanDevice.h" supp="0" total="3"/>
                  <Res name="VulkanSyncObjects.cpp" supp="0" total="0"/>
                  <Res name="VulkanDescriptorSet.cpp" supp="0" total="0"/>
                  <Res loc="TheOrb/TheOrb/Source Files/src/vulkan/VulkanSwapChain.h" locType="sr" name="VulkanSwapChain.h" supp="0" total="11"/>
               </Res>
               <Res name="Source Files/src/rendering" supp="0" total="30">
                  <Res name="Cubemap.h" supp="0" total="0"/>
                  <Res loc="TheOrb/TheOrb/Source Files/src/rendering/Scene.cpp" locType="sr" name="Scene.cpp" supp="0" total="1"/>
                  <Res loc="TheOrb/TheOrb/Source Files/src/rendering/SkyboxPass.cpp" locType="sr" name="SkyboxPass.cpp" supp="0" total="2"/>
                  <Res loc="TheOrb/TheOrb/Source Files/src/rendering/Renderer.cpp" locType="sr" name="Renderer.cpp" supp="0" total="1"/>
                  <Res loc="TheOrb/TheOrb/Source Files/src/rendering/ShadowPass.h" locType="sr" name="ShadowPass.h" supp="0" total="2"/>
                  <Res loc="TheOrb/TheOrb/Source Files/src/rendering/SkyboxPass.h" locType="sr" name="SkyboxPass.h" supp="0" total="2"/>
                  <Res loc="TheOrb/TheOrb/Source Files/src/rendering/GraphicsPipeline.h" locType="sr" name="GraphicsPipeline.h" supp="0" total="1"/>
                  <Res name="Cubemap.cpp" supp="0" total="0"/>
                  <Res loc="TheOrb/TheOrb/Source Files/src/rendering/Texture.cpp" locType="sr" name="Texture.cpp" supp="0" total="2"/>
                  <Res loc="TheOrb/TheOrb/Source Files/src/rendering/ParticleSystem.h" locType="sr" name="ParticleSystem.h" supp="0" total="5"/>
                  <Res name="ParticleLibrary.h" supp="0" total="0"/>
                  <Res name="ShadowPass.cpp" supp="0" total="0"/>
                  <Res name="Texture.h" supp="0" total="0"/>
                  <Res name="GraphicsPipeline.cpp" supp="0" total="0"/>
                  <Res name="CameraController.cpp" supp="0" total="0"/>
                  <Res name="Camera.cpp" supp="0" total="0"/>
                  <Res loc="TheOrb/TheOrb/Source Files/src/rendering/Camera.h" locType="sr" name="Camera.h" supp="0" total="3"/>
                  <Res name="CameraController.h" supp="0" total="0"/>
                  <Res loc="TheOrb/TheOrb/Source Files/src/rendering/Renderer.h" locType="sr" name="Renderer.h" supp="0" total="1"/>
                  <Res loc="TheOrb/TheOrb/Source Files/src/rendering/ParticleLibrary.cpp" locType="sr" name="ParticleLibrary.cpp" supp="0" total="1"/>
                  <Res loc="TheOrb/TheOrb/Source Files/src/rendering/ParticleSystem.cpp" locType="sr" name="ParticleSystem.cpp" supp="0" total="2"/>
                  <Res loc="TheOrb/TheOrb/Source Files/src/rendering/Scene.h" locType="sr" name="Scene.h" supp="0" total="7"/>
               </Res>
               <Res name="Source Files/src" supp="0" total="0">
                  <Res name="main.cpp" supp="0" total="0"/>
               </Res>
               <Res name="Source Files/src/core" supp="0" total="2">
                  <Res loc="TheOrb/TheOrb/Source Files/src/core/Window.h" locType="sr" name="Window.h" supp="0" total="1"/>
                  <Res loc="TheOrb/TheOrb/Source Files/src/core/Window.cpp" locType="sr" name="Window.cpp" supp="0" total="1"/>
                  <Res name="Application.h" supp="0" total="0"/>
                  <Res name="Application.cpp" supp="0" total="0"/>
               </Res>
            </Project>
         </Total>
      </TestedFilesDetails>
   </CodingStandards>
</ResultsSession>
